oops/__init__.py
oops/config.py
oops/createhooks.py
oops/publishers.py
oops-0.1.0.dist-info/licenses/LICENSE
oops-0.1.0.dist-info/METADATA
oops-0.1.0.dist-info/WHEEL
oops-0.1.0.dist-info/top_level.txt
oops-0.1.0.dist-info/RECORD
